joshbasiccalculator/__init__.py
alsaidi-0.0.1.dist-info/LICENCE.txt
alsaidi-0.0.1.dist-info/METADATA
alsaidi-0.0.1.dist-info/WHEEL
alsaidi-0.0.1.dist-info/top_level.txt
alsaidi-0.0.1.dist-info/RECORD
