Metadata-Version: 2.1
Name: alsaidi
Version: 0.0.1
Summary: simple code for alsaidi
Home-page: UNKNOWN
Author: alsaidi
Author-email: hashemshaiban@gmail.com
License: MIT
Keywords: alsaidi
Platform: UNKNOWN
Classifier: Development Status :: 5 - Production/Stable
Classifier: Intended Audience :: Education
Classifier: Operating System :: Microsoft :: Windows :: Windows 10
Classifier: License :: OSI Approved :: MIT License
Classifier: Programming Language :: Python :: 3
License-File: LICENCE.txt
